{
  "content": [
    {
      "content": null,
      "created": "2024-08-26T10:40:31.689621Z",
      "format": null,
      "hash": null,
      "hash_algorithm": null,
      "last_modified": "2024-08-26T10:40:29.113654Z",
      "mimetype": null,
      "name": "different_calibration_curves.ipynb",
      "path": "notebooks/different_calibration_curves.ipynb",
      "size": 11481,
      "type": "notebook",
      "writable": true
    },
    {
      "content": null,
      "created": "2024-08-26T10:40:31.689621Z",
      "format": null,
      "hash": null,
      "hash_algorithm": null,
      "last_modified": "2024-08-26T10:40:29.101655Z",
      "mimetype": null,
      "name": "cost_sensitive_learning.ipynb",
      "path": "notebooks/cost_sensitive_learning.ipynb",
      "size": 36660,
      "type": "notebook",
      "writable": true
    },
    {
      "content": null,
      "created": "2024-08-26T10:40:31.689621Z",
      "format": null,
      "hash": null,
      "hash_algorithm": null,
      "last_modified": "2024-08-26T10:40:29.065655Z",
      "mimetype": null,
      "name": "build_calibration_curve.ipynb",
      "path": "notebooks/build_calibration_curve.ipynb",
      "size": 12668,
      "type": "notebook",
      "writable": true
    },
    {
      "content": null,
      "created": "2024-08-26T10:40:31.689621Z",
      "format": null,
      "hash": null,
      "hash_algorithm": null,
      "last_modified": "2024-08-26T10:40:29.049655Z",
      "mimetype": null,
      "name": "_generate_predictions.ipynb",
      "path": "notebooks/_generate_predictions.ipynb",
      "size": 2900,
      "type": "notebook",
      "writable": true
    },
    {
      "content": null,
      "created": "2024-08-26T10:40:31.689621Z",
      "format": null,
      "hash": null,
      "hash_algorithm": null,
      "last_modified": "2024-08-26T10:40:29.121654Z",
      "mimetype": null,
      "name": "miscalibration_reweighting.ipynb",
      "path": "notebooks/miscalibration_reweighting.ipynb",
      "size": 12947,
      "type": "notebook",
      "writable": true
    },
    {
      "content": null,
      "created": "2024-08-26T10:40:31.689621Z",
      "format": null,
      "hash": null,
      "hash_algorithm": null,
      "last_modified": "2024-08-26T10:40:29.073655Z",
      "mimetype": null,
      "name": "classification_metrics.ipynb",
      "path": "notebooks/classification_metrics.ipynb",
      "size": 10685,
      "type": "notebook",
      "writable": true
    },
    {
      "content": null,
      "created": "2024-08-26T10:40:31.689621Z",
      "format": null,
      "hash": null,
      "hash_algorithm": null,
      "last_modified": "2024-08-26T10:40:29.145654Z",
      "mimetype": null,
      "name": "miscalibration_under_over_fit.ipynb",
      "path": "notebooks/miscalibration_under_over_fit.ipynb",
      "size": 32491,
      "type": "notebook",
      "writable": true
    }
  ],
  "created": "2024-08-26T10:40:31.689621Z",
  "format": "json",
  "hash": null,
  "hash_algorithm": null,
  "last_modified": "2024-08-26T10:40:31.689621Z",
  "mimetype": null,
  "name": "notebooks",
  "path": "notebooks",
  "size": null,
  "type": "directory",
  "writable": true
}